{
    "name": "Huawei | CX200-CX300 | CX31SCUB",
    "$collection": "inv.objectmodels",
    "uuid": "dea99474-6dce-44f3-9a45-6196999ead05",
    "vendor__code": "HUAWEI",
    "description": "General Switch Control Unit B(24G Switch Capacity)",
    "cr_context": "SCU",
    "labels": ["noc::inv::lc", "noc::inv::sup", "noc::inv::fabric"],
    "connections": [
        {
            "name": "in",
            "description": null,
            "direction": "o",
            "gender": "m",
            "type__name": "Huawei | CX200-300 | SCU"
        },
        {
            "name": "aux",
            "description": "Aux port",
            "direction": "s",
            "gender": "f",
            "protocols": [
                {
                    "direction": "<",
                    "protocol__code": "RS232"
                },
                {
                    "direction": ">",
                    "protocol__code": "RS232"
                }
            ],
            "type__name": "Electrical | RJ45"
        },
        {
            "name": "console",
            "description": "Console for on-site system configuration",
            "direction": "s",
            "gender": "f",
            "protocols": [{
                "direction": ">",
                "protocol__code": "RS232"
            }],
            "type__name": "Electrical | RJ45"
        },
        {
            "name": "MEth0/0/1",
            "description": "Management port",
            "direction": "s",
            "gender": "f",
            "protocols": [
                {
                    "direction": "*",
                    "protocol__code": "10BASET"
                },
                {
                    "direction": "*",
                    "protocol__code": "100BASETX"
                }
            ],
            "type__name": "Electrical | RJ45"
        }
    ],
    "data": [
        {
            "attr": "order_part_no",
            "interface": "asset",
            "value": ["03030BEG"]
        },
        {
            "attr": "part_no",
            "interface": "asset",
            "value": ["CX31SCUB"]
        }
    ]
}
