{
    "name": "Cisco | IOS | Network | PIM | Neighbor Down #2 (SYSLOG)",
    "uuid": "e1d91bf7-3b79-4d30-abd9-c1ce7835a59e",
    "description": "%PIM-5-NBRCHG: VRF shpd: neighbor 172.18.228.154 DOWN on interface Vlan884 DR",
    "event_class__name": "Network | PIM | Neighbor Down",
    "preference": 1000,
    "patterns": [
        {
            "key_re": "^source$",
            "value_re": "^syslog$"
        },
        {
            "key_re": "^profile$",
            "value_re": "^Cisco\\.IOS$"
        },
        {
            "key_re": "^message$",
            "value_re": "%PIM-5-NBRCHG: VRF (?P<vrf>\\S+): neighbor (?P<neighbor>\\S+) DOWN on interface (?P<interface>\\S+)( non)? DR"
        }
    ]
}