{
    "name": "Cisco | ISR | Module | WIC-2T",
    "$collection": "inv.objectmodels",
    "uuid": "e330dc06-8aac-43db-9555-f5857d1d9cec",
    "vendor__code": "CISCO",
    "description": "2 Port Serial WAN Interface Card",
    "cr_context": "DCS",
    "connections": [
        {
            "description": "Voice WAN Interface Card connector",
            "direction": "o",
            "gender": "m",
            "name": "in",
            "protocols": ["VWIC", "WIC"],
            "type__name": "Cisco | ISR | DCS"
        },
        {
            "description": "Serial0",
            "direction": "s",
            "gender": "f",
            "name": "Se0",
            "protocols": ["T1"],
            "type__name": "Electrical | SmartSerial"
        },
        {
            "description": "Serial1",
            "direction": "s",
            "gender": "f",
            "name": "Se1",
            "protocols": ["T1"],
            "type__name": "Electrical | SmartSerial"
        }
    ],
    "data": {
        "asset": {
            "part_no": ["WIC-2T="]
        }
    }
}
