{
    "name": "Juniper | EX | EX9200-40F",
    "$collection": "inv.objectmodels",
    "uuid": "ed559c5b-19da-4044-961d-eb1e8f69bb79",
    "vendor__code": "JUNIPER",
    "description": "40x1GE Enhanced DPC for EX9200",
    "cr_context": "FPC",
    "labels": ["noc::inv::lc", "noc::inv::fabric"],
    "connections": [
        {
            "name": "mic0",
            "description": "MIC0 slot",
            "direction": "i",
            "gender": "f",
            "type__name": "Juniper | MX | MIC"
        },
        {
            "name": "mic1",
            "description": "MIC1 slot",
            "direction": "i",
            "gender": "f",
            "type__name": "Juniper | MX | MIC"
        },
        {
            "name": "in",
            "description": "Inner connector",
            "direction": "o",
            "gender": "m",
            "type__name": "Juniper | MX | FPC"
        }
    ],
    "data": [
        {
            "attr": "order_part_no",
            "interface": "asset",
            "value": ["EX9200-40F"]
        },
        {
            "attr": "part_no",
            "interface": "asset",
            "value": ["750-049766", "750-064570"]
        }
    ]
}
