{
    "name": "Huawei | Quidway S5300 | S5300-10P-LI-AC",
    "$collection": "inv.objectmodels",
    "uuid": "4f5697b5-e079-41be-b593-2d204f11b3e6",
    "vendor__code": "HUAWEI",
    "description": "Quidway S5300-10P-LI-AC,S5300-10P-LI-AC,S5300-10P-LI-AC Mainframe(8 GE RJ45,2 GE SFP,AC 110/220V)",
    "connection_rule__name": "Huawei | Quidway",
    "cr_context": "CHASSIS",
    "labels": [
        "noc::inv::chassis",
        "noc::inv::sup",
        "noc::inv::psu",
        "noc::inv::fabric",
        "noc::inv::fan",
        "noc::inv::port"
    ],
    "connections": [
        {
            "name": "power",
            "description": "Power outlet",
            "direction": "s",
            "gender": "m",
            "protocols": [
                {
                    "direction": ">",
                    "protocol__code": "220VAC"
                },
                {
                    "direction": ">",
                    "protocol__code": "110VAC"
                }
            ],
            "type__name": "Power | IEC 60320 C14"
        },
        {
            "name": "Console",
            "description": "Management Console",
            "direction": "s",
            "gender": "f",
            "protocols": [{
                "direction": ">",
                "protocol__code": "RS232"
            }],
            "type__name": "Electrical | RJ45"
        },
        {
            "name": "usb0",
            "description": "USB port",
            "direction": "s",
            "gender": "f",
            "protocols": [
                {
                    "direction": "*",
                    "protocol__code": "USB10"
                },
                {
                    "direction": "*",
                    "protocol__code": "USB11"
                },
                {
                    "direction": "*",
                    "protocol__code": "USB20"
                }
            ],
            "type__name": "Electrical | mini-USB"
        },
        {
            "name": "GigabitEthernet0/0/1",
            "description": "GigabitEthernet 0/0/1 port",
            "direction": "s",
            "gender": "f",
            "protocols": [
                {
                    "direction": "*",
                    "protocol__code": "10BASET"
                },
                {
                    "direction": "*",
                    "protocol__code": "100BASETX"
                },
                {
                    "direction": "*",
                    "protocol__code": "1000BASETX"
                }
            ],
            "type__name": "Electrical | RJ45"
        },
        {
            "name": "GigabitEthernet0/0/2",
            "description": "GigabitEthernet 0/0/2 port",
            "direction": "s",
            "gender": "f",
            "protocols": [
                {
                    "direction": "*",
                    "protocol__code": "10BASET"
                },
                {
                    "direction": "*",
                    "protocol__code": "100BASETX"
                },
                {
                    "direction": "*",
                    "protocol__code": "1000BASETX"
                }
            ],
            "type__name": "Electrical | RJ45"
        },
        {
            "name": "GigabitEthernet0/0/3",
            "description": "GigabitEthernet 0/0/3 port",
            "direction": "s",
            "gender": "f",
            "protocols": [
                {
                    "direction": "*",
                    "protocol__code": "10BASET"
                },
                {
                    "direction": "*",
                    "protocol__code": "100BASETX"
                },
                {
                    "direction": "*",
                    "protocol__code": "1000BASETX"
                }
            ],
            "type__name": "Electrical | RJ45"
        },
        {
            "name": "GigabitEthernet0/0/4",
            "description": "GigabitEthernet 0/0/4 port",
            "direction": "s",
            "gender": "f",
            "protocols": [
                {
                    "direction": "*",
                    "protocol__code": "10BASET"
                },
                {
                    "direction": "*",
                    "protocol__code": "100BASETX"
                },
                {
                    "direction": "*",
                    "protocol__code": "1000BASETX"
                }
            ],
            "type__name": "Electrical | RJ45"
        },
        {
            "name": "GigabitEthernet0/0/5",
            "description": "GigabitEthernet 0/0/5 port",
            "direction": "s",
            "gender": "f",
            "protocols": [
                {
                    "direction": "*",
                    "protocol__code": "10BASET"
                },
                {
                    "direction": "*",
                    "protocol__code": "100BASETX"
                },
                {
                    "direction": "*",
                    "protocol__code": "1000BASETX"
                }
            ],
            "type__name": "Electrical | RJ45"
        },
        {
            "name": "GigabitEthernet0/0/6",
            "description": "GigabitEthernet 0/0/6 port",
            "direction": "s",
            "gender": "f",
            "protocols": [
                {
                    "direction": "*",
                    "protocol__code": "10BASET"
                },
                {
                    "direction": "*",
                    "protocol__code": "100BASETX"
                },
                {
                    "direction": "*",
                    "protocol__code": "1000BASETX"
                }
            ],
            "type__name": "Electrical | RJ45"
        },
        {
            "name": "GigabitEthernet0/0/7",
            "description": "GigabitEthernet 0/0/7 port",
            "direction": "s",
            "gender": "f",
            "protocols": [
                {
                    "direction": "*",
                    "protocol__code": "10BASET"
                },
                {
                    "direction": "*",
                    "protocol__code": "100BASETX"
                },
                {
                    "direction": "*",
                    "protocol__code": "1000BASETX"
                }
            ],
            "type__name": "Electrical | RJ45"
        },
        {
            "name": "GigabitEthernet0/0/8",
            "description": "GigabitEthernet 0/0/8 port",
            "direction": "s",
            "gender": "f",
            "protocols": [
                {
                    "direction": "*",
                    "protocol__code": "10BASET"
                },
                {
                    "direction": "*",
                    "protocol__code": "100BASETX"
                },
                {
                    "direction": "*",
                    "protocol__code": "1000BASETX"
                }
            ],
            "type__name": "Electrical | RJ45"
        },
        {
            "name": "GigabitEthernet0/0/9",
            "description": "GigabitEthernet 0/0/9 SFP port",
            "direction": "i",
            "gender": "f",
            "internal_name": "Port_GigabitEthernet0/0/9",
            "protocols": [
                {
                    "direction": "*",
                    "protocol__code": "TransEth100M"
                },
                {
                    "direction": "*",
                    "protocol__code": "TransEth1G"
                }
            ],
            "type__name": "Transceiver | SFP"
        },
        {
            "name": "GigabitEthernet0/0/10",
            "description": "GigabitEthernet 0/0/10 SFP port",
            "direction": "i",
            "gender": "f",
            "internal_name": "Port_GigabitEthernet0/0/10",
            "protocols": [
                {
                    "direction": "*",
                    "protocol__code": "TransEth100M"
                },
                {
                    "direction": "*",
                    "protocol__code": "TransEth1G"
                }
            ],
            "type__name": "Transceiver | SFP"
        }
    ],
    "data": [
        {
            "attr": "managed",
            "interface": "management",
            "value": true
        },
        {
            "attr": "width",
            "interface": "dimensions",
            "value": 250
        },
        {
            "attr": "depth",
            "interface": "dimensions",
            "value": 180
        },
        {
            "attr": "height",
            "interface": "dimensions",
            "value": 43
        },
        {
            "attr": "power",
            "interface": "power",
            "value": 10.0
        },
        {
            "attr": "weight",
            "interface": "weight",
            "value": 1.4
        },
        {
            "attr": "part_no",
            "interface": "asset",
            "value": ["S5300-10P-LI-AC"]
        },
        {
            "attr": "units",
            "interface": "rackmount",
            "value": 1.0
        }
    ]
}
