{
    "name": "Juniper | MX | MIC3-3D-10XGE-SFPP",
    "$collection": "inv.objectmodels",
    "uuid": "fd408a9e-17ea-4dec-b40c-ec1e1a71299c",
    "vendor__code": "JUNIPER",
    "description": "MIC with 10 10-Gigabit Ethernet SFP+ ports",
    "connection_rule__name": "Juniper | MX",
    "cr_context": "MIC",
    "connections": [
        {
            "name": "in",
            "description": "FPC connection",
            "direction": "o",
            "gender": "m",
            "type__name": "Juniper | MX | MIC"
        },
        {
            "name": "0/0",
            "description": "Port 0/0",
            "direction": "i",
            "gender": "f",
            "protocols": [{
                "direction": "*",
                "protocol__code": "TransEth10G"
            }],
            "type__name": "Transceiver | SFP+"
        },
        {
            "name": "0/1",
            "description": "Port 0/1",
            "direction": "i",
            "gender": "f",
            "protocols": [{
                "direction": "*",
                "protocol__code": "TransEth10G"
            }],
            "type__name": "Transceiver | SFP+"
        },
        {
            "name": "0/2",
            "description": "Port 0/2",
            "direction": "i",
            "gender": "f",
            "protocols": [{
                "direction": "*",
                "protocol__code": "TransEth10G"
            }],
            "type__name": "Transceiver | SFP+"
        },
        {
            "name": "0/3",
            "description": "Port 0/3",
            "direction": "i",
            "gender": "f",
            "protocols": [{
                "direction": "*",
                "protocol__code": "TransEth10G"
            }],
            "type__name": "Transceiver | SFP+"
        },
        {
            "name": "0/4",
            "description": "Port 0/4",
            "direction": "i",
            "gender": "f",
            "protocols": [{
                "direction": "*",
                "protocol__code": "TransEth10G"
            }],
            "type__name": "Transceiver | SFP+"
        },
        {
            "name": "0/5",
            "description": "Port 0/5",
            "direction": "i",
            "gender": "f",
            "protocols": [{
                "direction": "*",
                "protocol__code": "TransEth10G"
            }],
            "type__name": "Transceiver | SFP+"
        },
        {
            "name": "0/6",
            "description": "Port 0/6",
            "direction": "i",
            "gender": "f",
            "protocols": [{
                "direction": "*",
                "protocol__code": "TransEth10G"
            }],
            "type__name": "Transceiver | SFP+"
        },
        {
            "name": "0/7",
            "description": "Port 0/7",
            "direction": "i",
            "gender": "f",
            "protocols": [{
                "direction": "*",
                "protocol__code": "TransEth10G"
            }],
            "type__name": "Transceiver | SFP+"
        },
        {
            "name": "0/8",
            "description": "Port 0/8",
            "direction": "i",
            "gender": "f",
            "protocols": [{
                "direction": "*",
                "protocol__code": "TransEth10G"
            }],
            "type__name": "Transceiver | SFP+"
        },
        {
            "name": "0/9",
            "description": "Port 0/9",
            "direction": "i",
            "gender": "f",
            "protocols": [{
                "direction": "*",
                "protocol__code": "TransEth10G"
            }],
            "type__name": "Transceiver | SFP+"
        }
    ],
    "data": [
        {
            "attr": "part_no",
            "interface": "asset",
            "value": ["750-033307"]
        },
        {
            "attr": "order_part_no",
            "interface": "asset",
            "value": ["MIC3-3D-10XGE-SFPP"]
        }
    ]
}
