{
    "name": "Juniper | MX | SCBE3-MX-S",
    "$collection": "inv.objectmodels",
    "uuid": "1c9db00a-4790-4da4-9a96-2d86661ccb47",
    "vendor__code": "JUNIPER",
    "description": "MX Enhanced Switch Control Board",
    "cr_context": "SCB",
    "connections": [
        {
            "name": "re",
            "description": "Routing Engine slot",
            "direction": "i",
            "gender": "f",
            "type__name": "Juniper | MX | RE"
        },
        {
            "name": "in",
            "description": "Chassis connection",
            "direction": "o",
            "gender": "m",
            "type__name": "Juniper | MX | SCB"
        }
    ],
    "data": [
        {
            "attr": "part_no",
            "interface": "asset",
            "value": ["750-070866"]
        },
        {
            "attr": "order_part_no",
            "interface": "asset",
            "value": ["SCBE3-MX-S"]
        }
    ]
}
