{
    "name": "Huawei | CX600 | CX600-X8",
    "$collection": "inv.objectmodels",
    "uuid": "6118dcb4-99c7-4216-a314-932e90623a79",
    "vendor__code": "HUAWEI",
    "description": "CX600-X8 Integrated Chassis Components(Including 4 DC Power)",
    "connection_rule__name": "Huawei | CX",
    "cr_context": "CHASSIS",
    "labels": ["noc::inv::chassis"],
    "connections": [
        {
            "name": "1",
            "description": "LPU Slot #1",
            "direction": "i",
            "gender": "f",
            "type__name": "Huawei | CX&NE | LPU"
        },
        {
            "name": "2",
            "description": "LPU Slot #2",
            "direction": "i",
            "gender": "f",
            "type__name": "Huawei | CX&NE | LPU"
        },
        {
            "name": "3",
            "description": "LPU Slot #3",
            "direction": "i",
            "gender": "f",
            "type__name": "Huawei | CX&NE | LPU"
        },
        {
            "name": "4",
            "description": "LPU Slot #4",
            "direction": "i",
            "gender": "f",
            "type__name": "Huawei | CX&NE | LPU"
        },
        {
            "name": "5",
            "description": "LPU Slot #5",
            "direction": "i",
            "gender": "f",
            "type__name": "Huawei | CX&NE | LPU"
        },
        {
            "name": "6",
            "description": "LPU Slot #6",
            "direction": "i",
            "gender": "f",
            "type__name": "Huawei | CX&NE | LPU"
        },
        {
            "name": "7",
            "description": "LPU Slot #7",
            "direction": "i",
            "gender": "f",
            "type__name": "Huawei | CX&NE | LPU"
        },
        {
            "name": "8",
            "description": "LPU Slot #8",
            "direction": "i",
            "gender": "f",
            "type__name": "Huawei | CX&NE | LPU"
        },
        {
            "name": "9",
            "description": "SRU Slot #1",
            "direction": "i",
            "gender": "f",
            "type__name": "Huawei | CX&NE | SRU"
        },
        {
            "name": "10",
            "description": "SRU Slot #2",
            "direction": "i",
            "gender": "f",
            "type__name": "Huawei | CX&NE | SRU"
        },
        {
            "name": "11",
            "description": "SFU Slot #1",
            "direction": "i",
            "gender": "f",
            "type__name": "Huawei | CX&NE | SFU"
        },
        {
            "name": "A1",
            "description": "Power Slot A1",
            "direction": "i",
            "gender": "f",
            "type__name": "Huawei | CX&NE | CX600 PEM"
        },
        {
            "name": "A2",
            "description": "Power Slot A2",
            "direction": "i",
            "gender": "f",
            "type__name": "Huawei | CX&NE | CX600 PEM"
        },
        {
            "name": "A3",
            "description": "Fan Slot A3",
            "direction": "i",
            "gender": "f",
            "type__name": "Huawei | CX&NE | CX600 FAN"
        },
        {
            "name": "B1",
            "description": "Power Slot B1",
            "direction": "i",
            "gender": "f",
            "type__name": "Huawei | CX&NE | CX600 PEM"
        },
        {
            "name": "B2",
            "description": "Power Slot B2",
            "direction": "i",
            "gender": "f",
            "type__name": "Huawei | CX&NE | CX600 PEM"
        },
        {
            "name": "B3",
            "description": "Fan Slot B3",
            "direction": "i",
            "gender": "f",
            "type__name": "Huawei | CX&NE | CX600 FAN"
        }
    ],
    "data": [
        {
            "attr": "managed",
            "interface": "management",
            "value": true
        },
        {
            "attr": "width",
            "interface": "dimensions",
            "value": 442
        },
        {
            "attr": "depth",
            "interface": "dimensions",
            "value": 650
        },
        {
            "attr": "height",
            "interface": "dimensions",
            "value": 620
        },
        {
            "attr": "power",
            "interface": "power",
            "value": 3300.0
        },
        {
            "attr": "weight",
            "interface": "weight",
            "value": 130.0
        },
        {
            "attr": "part_no",
            "interface": "asset",
            "value": ["CX6Z1BKP08A"]
        },
        {
            "attr": "order_part_no",
            "interface": "asset",
            "value": ["02351932"]
        },
        {
            "attr": "units",
            "interface": "rackmount",
            "value": 14.0
        }
    ]
}
