{
    "name": "Cisco | C3560 | WS-C3560-24TS-S",
    "uuid": "13cd14fc-aaca-4e58-a9cc-2b97fd8cd084",
    "vendor__code": "CISCO",
    "description": "24 Ethernet 10/100 ports and 2 SFP-based Gigabit Ethernet ports",
    "connection_rule__name": "Generic | Switch SFP Prefixed",
    "connections": [
        {
            "description": "Fa0/1",
            "direction": "s",
            "gender": "f",
            "name": "Fa1",
            "protocols": ["10BASET", "100BASETX"],
            "type__name": "Electrical | RJ45"
        },
        {
            "description": "Fa0/2",
            "direction": "s",
            "gender": "f",
            "name": "Fa2",
            "protocols": ["10BASET", "100BASETX"],
            "type__name": "Electrical | RJ45"
        },
        {
            "description": "Fa0/3",
            "direction": "s",
            "gender": "f",
            "name": "Fa3",
            "protocols": ["10BASET", "100BASETX"],
            "type__name": "Electrical | RJ45"
        },
        {
            "description": "Fa0/4",
            "direction": "s",
            "gender": "f",
            "name": "Fa4",
            "protocols": ["10BASET", "100BASETX"],
            "type__name": "Electrical | RJ45"
        },
        {
            "description": "Fa0/5",
            "direction": "s",
            "gender": "f",
            "name": "Fa5",
            "protocols": ["10BASET", "100BASETX"],
            "type__name": "Electrical | RJ45"
        },
        {
            "description": "Fa0/6",
            "direction": "s",
            "gender": "f",
            "name": "Fa6",
            "protocols": ["10BASET", "100BASETX"],
            "type__name": "Electrical | RJ45"
        },
        {
            "description": "Fa0/7",
            "direction": "s",
            "gender": "f",
            "name": "Fa7",
            "protocols": ["10BASET", "100BASETX"],
            "type__name": "Electrical | RJ45"
        },
        {
            "description": "Fa0/8",
            "direction": "s",
            "gender": "f",
            "name": "Fa8",
            "protocols": ["10BASET", "100BASETX"],
            "type__name": "Electrical | RJ45"
        },
        {
            "description": "Fa0/9",
            "direction": "s",
            "gender": "f",
            "name": "Fa9",
            "protocols": ["10BASET", "100BASETX"],
            "type__name": "Electrical | RJ45"
        },
        {
            "description": "Fa0/10",
            "direction": "s",
            "gender": "f",
            "name": "Fa10",
            "protocols": ["10BASET", "100BASETX"],
            "type__name": "Electrical | RJ45"
        },
        {
            "description": "Fa0/11",
            "direction": "s",
            "gender": "f",
            "name": "Fa11",
            "protocols": ["10BASET", "100BASETX"],
            "type__name": "Electrical | RJ45"
        },
        {
            "description": "Fa0/12",
            "direction": "s",
            "gender": "f",
            "name": "Fa12",
            "protocols": ["10BASET", "100BASETX"],
            "type__name": "Electrical | RJ45"
        },
        {
            "description": "Fa0/13",
            "direction": "s",
            "gender": "f",
            "name": "Fa13",
            "protocols": ["10BASET", "100BASETX"],
            "type__name": "Electrical | RJ45"
        },
        {
            "description": "Fa0/14",
            "direction": "s",
            "gender": "f",
            "name": "Fa14",
            "protocols": ["10BASET", "100BASETX"],
            "type__name": "Electrical | RJ45"
        },
        {
            "description": "Fa0/15",
            "direction": "s",
            "gender": "f",
            "name": "Fa15",
            "protocols": ["10BASET", "100BASETX"],
            "type__name": "Electrical | RJ45"
        },
        {
            "description": "Fa0/16",
            "direction": "s",
            "gender": "f",
            "name": "Fa16",
            "protocols": ["10BASET", "100BASETX"],
            "type__name": "Electrical | RJ45"
        },
        {
            "description": "Fa0/17",
            "direction": "s",
            "gender": "f",
            "name": "Fa17",
            "protocols": ["10BASET", "100BASETX"],
            "type__name": "Electrical | RJ45"
        },
        {
            "description": "Fa0/18",
            "direction": "s",
            "gender": "f",
            "name": "Fa18",
            "protocols": ["10BASET", "100BASETX"],
            "type__name": "Electrical | RJ45"
        },
        {
            "description": "Fa0/19",
            "direction": "s",
            "gender": "f",
            "name": "Fa19",
            "protocols": ["10BASET", "100BASETX"],
            "type__name": "Electrical | RJ45"
        },
        {
            "description": "Fa0/20",
            "direction": "s",
            "gender": "f",
            "name": "Fa20",
            "protocols": ["10BASET", "100BASETX"],
            "type__name": "Electrical | RJ45"
        },
        {
            "description": "Fa0/21",
            "direction": "s",
            "gender": "f",
            "name": "Fa21",
            "protocols": ["10BASET", "100BASETX"],
            "type__name": "Electrical | RJ45"
        },
        {
            "description": "Fa0/22",
            "direction": "s",
            "gender": "f",
            "name": "Fa22",
            "protocols": ["10BASET", "100BASETX"],
            "type__name": "Electrical | RJ45"
        },
        {
            "description": "Fa0/23",
            "direction": "s",
            "gender": "f",
            "name": "Fa23",
            "protocols": ["10BASET", "100BASETX"],
            "type__name": "Electrical | RJ45"
        },
        {
            "description": "Fa0/24",
            "direction": "s",
            "gender": "f",
            "name": "Fa24",
            "protocols": ["10BASET", "100BASETX"],
            "type__name": "Electrical | RJ45"
        },
        {
            "description": "Gi0/1",
            "direction": "i",
            "gender": "f",
            "name": "Gi1_sfp",
            "protocols": ["TransEth100M", "TransEth1G"],
            "type__name": "Transceiver | SFP"
        },
        {
            "description": "Gi0/2",
            "direction": "i",
            "gender": "f",
            "name": "Gi2_sfp",
            "protocols": ["TransEth100M", "TransEth1G"],
            "type__name": "Transceiver | SFP"
        },
        {
            "description": "Console port",
            "direction": "s",
            "gender": "f",
            "name": "console",
            "protocols": [">RS232"],
            "type__name": "Electrical | RJ45"
        },
        {
            "description": "Power inlet",
            "direction": "s",
            "gender": "f",
            "name": "power",
            "protocols": [">220VAC", ">110VAC"],
            "type__name": "Power | IEC 60320 C14"
        }
    ],
    "data": {
        "asset": {
            "part_no0": "WS-C3560-24TS-S",
            "part_no1": "WS-C3560-24TS"
        },
        "management": {
            "managed": true
        },
        "rackmount": {
            "units": 1
        }
    }
}
