[
        {
        "name": "Juniper | MX | MIC-3D-20GE-SFP",
        "vendor__code": "JUNIPER",
        "description": "20x10/100/1000 MIC for MX",
        "connections": [
            {
                "description": "SFP 0/0",
                "direction": "i",
                "gender": "f",
                "name": "0/0",
                "type__name": "Transceiver | SFP"
            },
            {
                "description": "SFP 0/1",
                "direction": "i",
                "gender": "f",
                "name": "0/1",
                "type__name": "Transceiver | SFP"
            },
            {
                "description": "SFP 0/2",
                "direction": "i",
                "gender": "f",
                "name": "0/2",
                "type__name": "Transceiver | SFP"
            },
            {
                "description": "SFP 0/3",
                "direction": "i",
                "gender": "f",
                "name": "0/3",
                "type__name": "Transceiver | SFP"
            },
            {
                "description": "SFP 0/4",
                "direction": "i",
                "gender": "f",
                "name": "0/4",
                "type__name": "Transceiver | SFP"
            },
            {
                "description": "SFP 0/5",
                "direction": "i",
                "gender": "f",
                "name": "0/5",
                "type__name": "Transceiver | SFP"
            },
            {
                "description": "SFP 0/6",
                "direction": "i",
                "gender": "f",
                "name": "0/6",
                "type__name": "Transceiver | SFP"
            },
            {
                "description": "SFP 0/7",
                "direction": "i",
                "gender": "f",
                "name": "0/7",
                "type__name": "Transceiver | SFP"
            },
            {
                "description": "SFP 0/8",
                "direction": "i",
                "gender": "f",
                "name": "0/8",
                "type__name": "Transceiver | SFP"
            },
            {
                "description": "SFP 0/9",
                "direction": "i",
                "gender": "f",
                "name": "0/9",
                "type__name": "Transceiver | SFP"
            },
            {
                "description": "SFP 0/0",
                "direction": "i",
                "gender": "f",
                "name": "1/0",
                "type__name": "Transceiver | SFP"
            },
            {
                "description": "SFP 0/1",
                "direction": "i",
                "gender": "f",
                "name": "1/1",
                "type__name": "Transceiver | SFP"
            },
            {
                "description": "SFP 0/2",
                "direction": "i",
                "gender": "f",
                "name": "1/2",
                "type__name": "Transceiver | SFP"
            },
            {
                "description": "SFP 0/3",
                "direction": "i",
                "gender": "f",
                "name": "1/3",
                "type__name": "Transceiver | SFP"
            },
            {
                "description": "SFP 0/4",
                "direction": "i",
                "gender": "f",
                "name": "1/4",
                "type__name": "Transceiver | SFP"
            },
            {
                "description": "SFP 0/5",
                "direction": "i",
                "gender": "f",
                "name": "1/5",
                "type__name": "Transceiver | SFP"
            },
            {
                "description": "SFP 0/6",
                "direction": "i",
                "gender": "f",
                "name": "1/6",
                "type__name": "Transceiver | SFP"
            },
            {
                "description": "SFP 0/7",
                "direction": "i",
                "gender": "f",
                "name": "1/7",
                "type__name": "Transceiver | SFP"
            },
            {
                "description": "SFP 0/8",
                "direction": "i",
                "gender": "f",
                "name": "1/8",
                "type__name": "Transceiver | SFP"
            },
            {
                "description": "SFP 0/9",
                "direction": "i",
                "gender": "f",
                "name": "1/9",
                "type__name": "Transceiver | SFP"
            },
            {
                "description": "MPC connection",
                "direction": "o",
                "gender": "m",
                "name": "in",
                "type__name": "Juniper | MX | MIC"
            }
        ],
        "data": {
            "asset": {
                "order_part_no0": "MIC-3D-20GE-SFP",
                "part_no0": "750-028392"
            }
        }
    },

    {
        "name": "Juniper | MX | MIC-3D-4XGE-XFP",
        "vendor__code": "JUNIPER",
        "description": "4x10G MIC for MX",
        "connections": [
            {
                "description": "MPC connection",
                "direction": "o",
                "gender": "m",
                "group": "",
                "name": "in",
                "type__name": "Juniper | MX | MIC"
            },
            {
                "description": "Port 0",
                "direction": "i",
                "gender": "f",
                "group": "",
                "name": "0/0",
                "type__name": "Transceiver | XFP"
            },
            {
                "description": "Port 1",
                "direction": "i",
                "gender": "f",
                "group": "",
                "name": "0/1",
                "type__name": "Transceiver | XFP"
            },
            {
                "description": "Port 2",
                "direction": "i",
                "gender": "f",
                "group": "",
                "name": "1/0",
                "type__name": "Transceiver | XFP"
            },
            {
                "description": "Port 3",
                "direction": "i",
                "gender": "f",
                "group": "",
                "name": "1/1",
                "type__name": "Transceiver | XFP"
            }
        ],
        "data": {
            "asset": {
                "order_part_no0": "MIC-3D-4XGE-XFP",
                "part_no0": "750-028387"
            }
        }
    }
]
