{
    "name": "NOC | Unhandled Exception",
    "uuid": "f4f136da-b1db-4cf4-aede-9361337157f1",
    "description": "Get unhandled exception from system event",
    "event_class__name": "NOC | Unhandled Exception",
    "preference": 1000,
    "patterns": [
        {
            "key_re": "^component$",
            "value_re": "^(?P<component>\\S+)$"
        },
        {
            "key_re": "^traceback$",
            "value_re": "^UNHANDLED EXCEPTION.+?START OF TRACEBACK.+?(?P<traceback>File:\\s+(?P<file>.+?)\\s+\\(Line:\\s+(?P<line>\\d+)\\).+)END OF TRACEBACK"
        },
        {
            "key_re": "^type$",
            "value_re": "^Unhandled Exception$"
        },
        {
            "key_re": "^source$",
            "value_re": "^system$"
        },
        {
            "key_re": "^profile$",
            "value_re": "^NOC\\.SAE$"
        }
    ]
}